{ "_id" : { "$oid" : "50bebfb814b6500c5cb7979e" }, "CountryId" : 1, "Country" : "Afghanistan", "FIPS104" : "AF", "ISO2" : "AF", "ISO3" : "AFG", "ISON" : "4", "Internet" : "AF", "Capital" : "Kabul ", "MapReference" : "Asia ", "NationalitySingular" : "Afghan", "NationalityPlural" : "Afghans", "Currency" : "Afghani ", "CurrencyCode" : "AFA", "Population" : 26813057, "Title" : "Afghanistan", "Comment" : "" }
{ "_id" : { "$oid" : "50bebfb814b6500c5cb7979f" }, "CountryId" : 2, "Country" : "Albania", "FIPS104" : "AL", "ISO2" : "AL", "ISO3" : "ALB", "ISON" : "8", "Internet" : "AL", "Capital" : "Tirana ", "MapReference" : "Europe ", "NationalitySingular" : "Albanian", "NationalityPlural" : "Albanians", "Currency" : "Lek ", "CurrencyCode" : "ALL", "Population" : 3510484, "Title" : "Albania", "Comment" : "" }
{ "_id" : { "$oid" : "50bebfb914b6500c5cb797a0" }, "CountryId" : 3, "Country" : "Algeria", "FIPS104" : "AG", "ISO2" : "DZ", "ISO3" : "DZA", "ISON" : "12", "Internet" : "DZ", "Capital" : "Algiers ", "MapReference" : "Africa ", "NationalitySingular" : "Algerian", "NationalityPlural" : "Algerians", "Currency" : "Algerian Dinar ", "CurrencyCode" : "DZD", "Population" : 31736053, "Title" : "Algeria", "Comment" : "" }
{ "_id" : { "$oid" : "50bebfb914b6500c5cb797a1" }, "CountryId" : 4, "Country" : "American Samoa", "FIPS104" : "AQ", "ISO2" : "AS", "ISO3" : "ASM", "ISON" : "16", "Internet" : "AS", "Capital" : "Pago Pago ", "MapReference" : "Oceania ", "NationalitySingular" : "American Samoan", "NationalityPlural" : "American Samoans", "Currency" : "US Dollar", "CurrencyCode" : "USD", "Population" : 67084, "Title" : "American Samoa", "Comment" : "" }
{ "_id" : { "$oid" : "50bebfb914b6500c5cb797a2" }, "CountryId" : 5, "Country" : "Andorra", "FIPS104" : "AN", "ISO2" : "AD", "ISO3" : "AND", "ISON" : "20", "Internet" : "AD", "Capital" : "Andorra la Vella ", "MapReference" : "Europe ", "NationalitySingular" : "Andorran", "NationalityPlural" : "Andorrans", "Currency" : "Euro", "CurrencyCode" : "EUR", "Population" : 67627, "Title" : "Andorra", "Comment" : "" }
{ "_id" : { "$oid" : "50bebfba14b6500c5cb797a3" }, "CountryId" : 6, "Country" : "Angola", "FIPS104" : "AO", "ISO2" : "AO", "ISO3" : "AGO", "ISON" : "24", "Internet" : "AO", "Capital" : "Luanda ", "MapReference" : "Africa ", "NationalitySingular" : "Angolan", "NationalityPlural" : "Angolans", "Currency" : "Kwanza ", "CurrencyCode" : "AOA", "Population" : 10366031, "Title" : "Angola", "Comment" : "" }
{ "_id" : { "$oid" : "50bebfba14b6500c5cb797a4" }, "CountryId" : 7, "Country" : "Anguilla", "FIPS104" : "AV", "ISO2" : "AI", "ISO3" : "AIA", "ISON" : "660", "Internet" : "AI", "Capital" : "The Valley ", "MapReference" : "Central America and the Caribbean ", "NationalitySingular" : "Anguillan", "NationalityPlural" : "Anguillans", "Currency" : "East Caribbean Dollar ", "CurrencyCode" : "XCD", "Population" : 12132, "Title" : "Anguilla", "Comment" : "" }
{ "_id" : { "$oid" : "50bebfba14b6500c5cb797a5" }, "CountryId" : 8, "Country" : "Antarctica", "FIPS104" : "AY", "ISO2" : "AQ", "ISO3" : "ATA", "ISON" : "10", "Internet" : "AQ", "Capital" : "", "MapReference" : "Antarctic Region ", "NationalitySingular" : "", "NationalityPlural" : "", "Currency" : "", "CurrencyCode" : "", "Population" : 0, "Title" : "Antarctica", "Comment" : "ISO defines as the territory south of 60 degrees south latitude" }
{ "_id" : { "$oid" : "50bebfbb14b6500c5cb797a6" }, "CountryId" : 9, "Country" : "Antigua and Barbuda", "FIPS104" : "AC", "ISO2" : "AG", "ISO3" : "ATG", "ISON" : "28", "Internet" : "AG", "Capital" : "Saint John's ", "MapReference" : "Central America and the Caribbean ", "NationalitySingular" : "Antiguan and Barbudan", "NationalityPlural" : "Antiguans and Barbudans", "Currency" : "East Caribbean Dollar ", "CurrencyCode" : "XCD", "Population" : 66970, "Title" : "Antigua and Barbuda", "Comment" : "" }
{ "_id" : { "$oid" : "50bebfbc14b6500c5cb797a7" }, "CountryId" : 10, "Country" : "Argentina", "FIPS104" : "AR", "ISO2" : "AR", "ISO3" : "ARG", "ISON" : "32", "Internet" : "AR", "Capital" : "Buenos Aires ", "MapReference" : "South America ", "NationalitySingular" : "Argentine", "NationalityPlural" : "Argentines", "Currency" : "Argentine Peso ", "CurrencyCode" : "ARS", "Population" : 37384816, "Title" : "Argentina", "Comment" : "" }
{ "_id" : { "$oid" : "50bebfbc14b6500c5cb797a8" }, "CountryId" : 11, "Country" : "Armenia", "FIPS104" : "AM", "ISO2" : "AM", "ISO3" : "ARM", "ISON" : "51", "Internet" : "AM", "Capital" : "Yerevan ", "MapReference" : "Commonwealth of Independent States ", "NationalitySingular" : "Armenian", "NationalityPlural" : "Armenians", "Currency" : "Armenian Dram ", "CurrencyCode" : "AMD", "Population" : 3336100, "Title" : "Armenia", "Comment" : "" }
{ "_id" : { "$oid" : "50bebfbc14b6500c5cb797a9" }, "CountryId" : 12, "Country" : "Aruba", "FIPS104" : "AA", "ISO2" : "AW", "ISO3" : "ABW", "ISON" : "533", "Internet" : "AW", "Capital" : "Oranjestad ", "MapReference" : "Central America and the Caribbean ", "NationalitySingular" : "Aruban", "NationalityPlural" : "Arubans", "Currency" : "Aruban Guilder", "CurrencyCode" : "AWG", "Population" : 70007, "Title" : "Aruba", "Comment" : "" }
{ "_id" : { "$oid" : "50bebfbd14b6500c5cb797aa" }, "CountryId" : 13, "Country" : "Ashmore and Cartier", "FIPS104" : "AT", "ISO2" : "--", "ISO3" : "-- ", "ISON" : "--", "Internet" : "--", "Capital" : "", "MapReference" : "Southeast Asia ", "NationalitySingular" : "", "NationalityPlural" : "", "Currency" : "", "CurrencyCode" : "", "Population" : 0, "Title" : "Ashmore and Cartier", "Comment" : "ISO includes with Australia" }
{ "_id" : { "$oid" : "50bebfbd14b6500c5cb797ab" }, "CountryId" : 15, "Country" : "Austria", "FIPS104" : "AU", "ISO2" : "AT", "ISO3" : "AUT", "ISON" : "40", "Internet" : "AT", "Capital" : "Vienna ", "MapReference" : "Europe ", "NationalitySingular" : "Austrian", "NationalityPlural" : "Austrians", "Currency" : "Euro", "CurrencyCode" : "EUR", "Population" : 8150835, "Title" : "Austria", "Comment" : "" }
{ "_id" : { "$oid" : "50bebfbd14b6500c5cb797ac" }, "CountryId" : 16, "Country" : "Azerbaijan", "FIPS104" : "AJ", "ISO2" : "AZ", "ISO3" : "AZE", "ISON" : "31", "Internet" : "AZ", "Capital" : "Baku (Baki) ", "MapReference" : "Commonwealth of Independent States ", "NationalitySingular" : "Azerbaijani", "NationalityPlural" : "Azerbaijanis", "Currency" : "Azerbaijani Manat ", "CurrencyCode" : "AZM", "Population" : 7771092, "Title" : "Azerbaijan", "Comment" : "" }
{ "_id" : { "$oid" : "50bebfbe14b6500c5cb797ad" }, "CountryId" : 17, "Country" : "The Bahamas", "FIPS104" : "BF", "ISO2" : "BS", "ISO3" : "BHS", "ISON" : "44", "Internet" : "BS", "Capital" : "Nassau ", "MapReference" : "Central America and the Caribbean ", "NationalitySingular" : "Bahamian", "NationalityPlural" : "Bahamians", "Currency" : "Bahamian Dollar ", "CurrencyCode" : "BSD", "Population" : 297852, "Title" : "The Bahamas", "Comment" : "" }
{ "_id" : { "$oid" : "50bebfbe14b6500c5cb797ae" }, "CountryId" : 18, "Country" : "Bahrain", "FIPS104" : "BA", "ISO2" : "BH", "ISO3" : "BHR", "ISON" : "48", "Internet" : "BH", "Capital" : "Manama ", "MapReference" : "Middle East ", "NationalitySingular" : "Bahraini", "NationalityPlural" : "Bahrainis", "Currency" : "Bahraini Dinar ", "CurrencyCode" : "BHD", "Population" : 645361, "Title" : "Bahrain", "Comment" : "" }
{ "_id" : { "$oid" : "50bebfbe14b6500c5cb797af" }, "CountryId" : 19, "Country" : "Baker Island", "FIPS104" : "FQ", "ISO2" : "--", "ISO3" : "-- ", "ISON" : "--", "Internet" : "--", "Capital" : "", "MapReference" : "Oceania ", "NationalitySingular" : "", "NationalityPlural" : "", "Currency" : "", "CurrencyCode" : "", "Population" : 0, "Title" : "Baker Island", "Comment" : "ISO includes with the US Minor Outlying Islands" }
{ "_id" : { "$oid" : "50bebfbf14b6500c5cb797b0" }, "CountryId" : 20, "Country" : "Bangladesh", "FIPS104" : "BG", "ISO2" : "BD", "ISO3" : "BGD", "ISON" : "50", "Internet" : "BD", "Capital" : "Dhaka ", "MapReference" : "Asia ", "NationalitySingular" : "Bangladeshi", "NationalityPlural" : "Bangladeshis", "Currency" : "Taka ", "CurrencyCode" : "BDT", "Population" : 131269860, "Title" : "Bangladesh", "Comment" : "" }
{ "_id" : { "$oid" : "50bebfbf14b6500c5cb797b1" }, "CountryId" : 21, "Country" : "Barbados", "FIPS104" : "BB", "ISO2" : "BB", "ISO3" : "BRB", "ISON" : "52", "Internet" : "BB", "Capital" : "Bridgetown ", "MapReference" : "Central America and the Caribbean ", "NationalitySingular" : "Barbadian", "NationalityPlural" : "Barbadians", "Currency" : "Barbados Dollar", "CurrencyCode" : "BBD", "Population" : 275330, "Title" : "Barbados", "Comment" : "" }
{ "_id" : { "$oid" : "50bebfbf14b6500c5cb797b2" }, "CountryId" : 22, "Country" : "Bassas da India", "FIPS104" : "BS", "ISO2" : "--", "ISO3" : "-- ", "ISON" : "--", "Internet" : "--", "Capital" : "", "MapReference" : "Africa ", "NationalitySingular" : "", "NationalityPlural" : "", "Currency" : "", "CurrencyCode" : "", "Population" : 0, "Title" : "Bassas da India", "Comment" : "ISO includes with the Miscellaneous (French) Indian Ocean Islands" }
{ "_id" : { "$oid" : "50bebfc014b6500c5cb797b3" }, "CountryId" : 23, "Country" : "Belarus", "FIPS104" : "BO", "ISO2" : "BY", "ISO3" : "BLR", "ISON" : "112", "Internet" : "BY", "Capital" : "Minsk ", "MapReference" : "Commonwealth of Independent States ", "NationalitySingular" : "Belarusian", "NationalityPlural" : "Belarusians", "Currency" : "Belarussian Ruble", "CurrencyCode" : "BYR", "Population" : 10350194, "Title" : "Belarus", "Comment" : "" }
{ "_id" : { "$oid" : "50bebfc014b6500c5cb797b4" }, "CountryId" : 24, "Country" : "Belgium", "FIPS104" : "BE", "ISO2" : "BE", "ISO3" : "BEL", "ISON" : "56", "Internet" : "BE", "Capital" : "Brussels ", "MapReference" : "Europe ", "NationalitySingular" : "Belgian", "NationalityPlural" : "Belgians", "Currency" : "Euro", "CurrencyCode" : "EUR", "Population" : 10258762, "Title" : "Belgium", "Comment" : "" }
{ "_id" : { "$oid" : "50bebfc014b6500c5cb797b5" }, "CountryId" : 25, "Country" : "Belize", "FIPS104" : "BH", "ISO2" : "BZ", "ISO3" : "BLZ", "ISON" : "84", "Internet" : "BZ", "Capital" : "Belmopan ", "MapReference" : "Central America and the Caribbean ", "NationalitySingular" : "Belizean", "NationalityPlural" : "Belizeans", "Currency" : "Belize Dollar", "CurrencyCode" : "BZD", "Population" : 256062, "Title" : "Belize", "Comment" : "" }
{ "_id" : { "$oid" : "50bebfc114b6500c5cb797b6" }, "CountryId" : 26, "Country" : "Benin", "FIPS104" : "BN", "ISO2" : "BJ", "ISO3" : "BEN", "ISON" : "204", "Internet" : "BJ", "Capital" : "Porto-Novo  ", "MapReference" : "Africa ", "NationalitySingular" : "Beninese", "NationalityPlural" : "Beninese", "Currency" : "CFA Franc BCEAO", "CurrencyCode" : "XOF", "Population" : 6590782, "Title" : "Benin", "Comment" : "" }
{ "_id" : { "$oid" : "50bebfc114b6500c5cb797b7" }, "CountryId" : 27, "Country" : "Bermuda", "FIPS104" : "BD", "ISO2" : "BM", "ISO3" : "BMU", "ISON" : "60", "Internet" : "BM", "Capital" : "Hamilton ", "MapReference" : "North America ", "NationalitySingular" : "Bermudian", "NationalityPlural" : "Bermudians", "Currency" : "Bermudian Dollar ", "CurrencyCode" : "BMD", "Population" : 63503, "Title" : "Bermuda", "Comment" : "" }
{ "_id" : { "$oid" : "50bebfc114b6500c5cb797b8" }, "CountryId" : 28, "Country" : "Bhutan", "FIPS104" : "BT", "ISO2" : "BT", "ISO3" : "BTN", "ISON" : "64", "Internet" : "BT", "Capital" : "Thimphu ", "MapReference" : "Asia ", "NationalitySingular" : "Bhutanese", "NationalityPlural" : "Bhutanese", "Currency" : "Ngultrum", "CurrencyCode" : "BTN", "Population" : 2049412, "Title" : "Bhutan", "Comment" : "" }
{ "_id" : { "$oid" : "50bebfc214b6500c5cb797b9" }, "CountryId" : 29, "Country" : "Bolivia", "FIPS104" : "BL", "ISO2" : "BO", "ISO3" : "BOL", "ISON" : "68", "Internet" : "BO", "Capital" : "La Paz /Sucre ", "MapReference" : "South America ", "NationalitySingular" : "Bolivian", "NationalityPlural" : "Bolivians", "Currency" : "Boliviano ", "CurrencyCode" : "BOB", "Population" : 8300463, "Title" : "Bolivia", "Comment" : "" }
{ "_id" : { "$oid" : "50bebfc214b6500c5cb797ba" }, "CountryId" : 30, "Country" : "Bosnia and Herzegovina", "FIPS104" : "BK", "ISO2" : "BA", "ISO3" : "BIH", "ISON" : "70", "Internet" : "BA", "Capital" : "Sarajevo ", "MapReference" : "Bosnia and Herzegovina, Europe ", "NationalitySingular" : "Bosnian and Herzegovinian", "NationalityPlural" : "Bosnians and Herzegovinians", "Currency" : "Convertible Marka", "CurrencyCode" : "BAM", "Population" : 3922205, "Title" : "Bosnia and Herzegovina", "Comment" : "" }
{ "_id" : { "$oid" : "50bebfc214b6500c5cb797bb" }, "CountryId" : 31, "Country" : "Botswana", "FIPS104" : "BC", "ISO2" : "BW", "ISO3" : "BWA", "ISON" : "72", "Internet" : "BW", "Capital" : "Gaborone ", "MapReference" : "Africa ", "NationalitySingular" : "Motswana", "NationalityPlural" : "Batswana", "Currency" : "Pula ", "CurrencyCode" : "BWP", "Population" : 1586119, "Title" : "Botswana", "Comment" : "" }
{ "_id" : { "$oid" : "50bebfc314b6500c5cb797bc" }, "CountryId" : 32, "Country" : "Bouvet Island", "FIPS104" : "BV", "ISO2" : "BV", "ISO3" : "BVT", "ISON" : "74", "Internet" : "BV", "Capital" : "", "MapReference" : "Antarctic Region ", "NationalitySingular" : "", "NationalityPlural" : "", "Currency" : "Norwegian Krone ", "CurrencyCode" : "NOK", "Population" : 0, "Title" : "Bouvet Island", "Comment" : "" }
{ "_id" : { "$oid" : "50bebfc314b6500c5cb797bd" }, "CountryId" : 33, "Country" : "Brazil", "FIPS104" : "BR", "ISO2" : "BR", "ISO3" : "BRA", "ISON" : "76", "Internet" : "BR", "Capital" : "Brasilia ", "MapReference" : "South America ", "NationalitySingular" : "Brazilian", "NationalityPlural" : "Brazilians", "Currency" : "Brazilian Real ", "CurrencyCode" : "BRL", "Population" : 174468575, "Title" : "Brazil", "Comment" : "" }
{ "_id" : { "$oid" : "50bebfc414b6500c5cb797be" }, "CountryId" : 34, "Country" : "British Indian Ocean Territory", "FIPS104" : "IO", "ISO2" : "IO", "ISO3" : "IOT", "ISON" : "86", "Internet" : "IO", "Capital" : "", "MapReference" : "World ", "NationalitySingular" : "", "NationalityPlural" : "", "Currency" : "US Dollar", "CurrencyCode" : "USD", "Population" : 0, "Title" : "The British Indian Ocean Territory", "Comment" : "" }
{ "_id" : { "$oid" : "50bebfc414b6500c5cb797bf" }, "CountryId" : 35, "Country" : "British Virgin Islands", "FIPS104" : "VI", "ISO2" : "VG", "ISO3" : "VGB", "ISON" : "92", "Internet" : "VG", "Capital" : "Road Town ", "MapReference" : "Central America and the Caribbean ", "NationalitySingular" : "British Virgin Islander", "NationalityPlural" : "British Virgin Islanders", "Currency" : "US Dollar", "CurrencyCode" : "USD", "Population" : 20812, "Title" : "The British Virgin Islands", "Comment" : "" }
{ "_id" : { "$oid" : "50bebfc414b6500c5cb797c0" }, "CountryId" : 36, "Country" : "Brunei Darussalam", "FIPS104" : "BX", "ISO2" : "BN", "ISO3" : "BRN", "ISON" : "96", "Internet" : "BN", "Capital" : "", "MapReference" : "", "NationalitySingular" : "", "NationalityPlural" : "", "Currency" : "Brunei Dollar", "CurrencyCode" : "BND", "Population" : 372361, "Title" : "Brunei", "Comment" : "" }
{ "_id" : { "$oid" : "50bebfc514b6500c5cb797c1" }, "CountryId" : 37, "Country" : "Bulgaria", "FIPS104" : "BU", "ISO2" : "BG", "ISO3" : "BGR", "ISON" : "100", "Internet" : "BG", "Capital" : "Sofia ", "MapReference" : "Europe ", "NationalitySingular" : "Bulgarian", "NationalityPlural" : "Bulgarians", "Currency" : "Lev ", "CurrencyCode" : "BGN", "Population" : 7707495, "Title" : "Bulgaria", "Comment" : "" }
{ "_id" : { "$oid" : "50bebfc614b6500c5cb797c2" }, "CountryId" : 38, "Country" : "Burkina Faso", "FIPS104" : "UV", "ISO2" : "BF", "ISO3" : "BFA", "ISON" : "854", "Internet" : "BF", "Capital" : "Ouagadougou ", "MapReference" : "Africa ", "NationalitySingular" : "Burkinabe", "NationalityPlural" : "Burkinabe", "Currency" : "CFA Franc BCEAO", "CurrencyCode" : "XOF", "Population" : 12272289, "Title" : "Burkina Faso", "Comment" : "" }
{ "_id" : { "$oid" : "50bebfc714b6500c5cb797c3" }, "CountryId" : 39, "Country" : "Burma", "FIPS104" : "BM", "ISO2" : "MM", "ISO3" : "MMR", "ISON" : "104", "Internet" : "MM", "Capital" : "Rangoon ", "MapReference" : "Southeast Asia ", "NationalitySingular" : "Burmese", "NationalityPlural" : "Burmese", "Currency" : "kyat ", "CurrencyCode" : "MMK", "Population" : 41994678, "Title" : "Burma", "Comment" : "ISO uses the name Myanmar" }
{ "_id" : { "$oid" : "50bebfc714b6500c5cb797c4" }, "CountryId" : 40, "Country" : "Burundi", "FIPS104" : "BY", "ISO2" : "BI", "ISO3" : "BDI", "ISON" : "108", "Internet" : "BI", "Capital" : "Bujumbura ", "MapReference" : "Africa ", "NationalitySingular" : "Burundi", "NationalityPlural" : "Burundians", "Currency" : "Burundi Franc ", "CurrencyCode" : "BIF", "Population" : 6223897, "Title" : "Burundi", "Comment" : "" }
{ "_id" : { "$oid" : "50bebfc714b6500c5cb797c5" }, "CountryId" : 41, "Country" : "Cambodia", "FIPS104" : "CB", "ISO2" : "KH", "ISO3" : "KHM", "ISON" : "116", "Internet" : "KH", "Capital" : "Phnom Penh ", "MapReference" : "Southeast Asia ", "NationalitySingular" : "Cambodian", "NationalityPlural" : "Cambodians", "Currency" : "Riel ", "CurrencyCode" : "KHR", "Population" : 12491501, "Title" : "Cambodia", "Comment" : "" }
{ "_id" : { "$oid" : "50bebfc814b6500c5cb797c6" }, "CountryId" : 42, "Country" : "Cameroon", "FIPS104" : "CM", "ISO2" : "CM", "ISO3" : "CMR", "ISON" : "120", "Internet" : "CM", "Capital" : "Yaounde ", "MapReference" : "Africa ", "NationalitySingular" : "Cameroonian", "NationalityPlural" : "Cameroonians", "Currency" : "CFA Franc BEAC", "CurrencyCode" : "XAF", "Population" : 15803220, "Title" : "Cameroon", "Comment" : "" }
{ "_id" : { "$oid" : "50bebfc814b6500c5cb797c7" }, "CountryId" : 44, "Country" : "Cape Verde", "FIPS104" : "CV", "ISO2" : "CV", "ISO3" : "CPV", "ISON" : "132", "Internet" : "CV", "Capital" : "Praia ", "MapReference" : "World ", "NationalitySingular" : "Cape Verdean", "NationalityPlural" : "Cape Verdeans", "Currency" : "Cape Verdean Escudo ", "CurrencyCode" : "CVE", "Population" : 405163, "Title" : "Cape Verde", "Comment" : "" }
{ "_id" : { "$oid" : "50bebfc814b6500c5cb797c8" }, "CountryId" : 45, "Country" : "Cayman Islands", "FIPS104" : "CJ", "ISO2" : "KY", "ISO3" : "CYM", "ISON" : "136", "Internet" : "KY", "Capital" : "George Town ", "MapReference" : "Central America and the Caribbean ", "NationalitySingular" : "Caymanian", "NationalityPlural" : "Caymanians", "Currency" : "Cayman Islands Dollar", "CurrencyCode" : "KYD", "Population" : 35527, "Title" : "The Cayman Islands", "Comment" : "" }
{ "_id" : { "$oid" : "50bebfc914b6500c5cb797c9" }, "CountryId" : 46, "Country" : "Central African Republic", "FIPS104" : "CT", "ISO2" : "CF", "ISO3" : "CAF", "ISON" : "140", "Internet" : "CF", "Capital" : "Bangui ", "MapReference" : "Africa ", "NationalitySingular" : "Central African", "NationalityPlural" : "Central Africans", "Currency" : "CFA Franc BEAC", "CurrencyCode" : "XAF", "Population" : 3576884, "Title" : "The Central African Republic", "Comment" : "" }
{ "_id" : { "$oid" : "50bebfc914b6500c5cb797ca" }, "CountryId" : 47, "Country" : "Chad", "FIPS104" : "CD", "ISO2" : "TD", "ISO3" : "TCD", "ISON" : "148", "Internet" : "TD", "Capital" : "N'Djamena ", "MapReference" : "Africa ", "NationalitySingular" : "Chadian", "NationalityPlural" : "Chadians", "Currency" : "CFA Franc BEAC", "CurrencyCode" : "XAF", "Population" : 8707078, "Title" : "Chad", "Comment" : "" }
{ "_id" : { "$oid" : "50bebfc914b6500c5cb797cb" }, "CountryId" : 48, "Country" : "Chile", "FIPS104" : "CI", "ISO2" : "CL", "ISO3" : "CHL", "ISON" : "152", "Internet" : "CL", "Capital" : "Santiago ", "MapReference" : "South America ", "NationalitySingular" : "Chilean", "NationalityPlural" : "Chileans", "Currency" : "Chilean Peso ", "CurrencyCode" : "CLP", "Population" : 15328467, "Title" : "Chile", "Comment" : "" }
{ "_id" : { "$oid" : "50bebfca14b6500c5cb797cc" }, "CountryId" : 50, "Country" : "Christmas Island", "FIPS104" : "KT", "ISO2" : "CX", "ISO3" : "CXR", "ISON" : "162", "Internet" : "CX", "Capital" : "The Settlement ", "MapReference" : "Southeast Asia ", "NationalitySingular" : "Christmas Island", "NationalityPlural" : "Christmas Islanders", "Currency" : "Australian Dollar ", "CurrencyCode" : "AUD", "Population" : 2771, "Title" : "Christmas Island", "Comment" : "" }
{ "_id" : { "$oid" : "50bebfca14b6500c5cb797cd" }, "CountryId" : 51, "Country" : "Clipperton Island", "FIPS104" : "IP", "ISO2" : "--", "ISO3" : "-- ", "ISON" : "--", "Internet" : "--", "Capital" : "", "MapReference" : "World ", "NationalitySingular" : "", "NationalityPlural" : "", "Currency" : "", "CurrencyCode" : "", "Population" : 0, "Title" : "Clipperton Island", "Comment" : "ISO includes with French Polynesia" }
{ "_id" : { "$oid" : "50bebfcb14b6500c5cb797ce" }, "CountryId" : 52, "Country" : "Cocos (Keeling) Islands", "FIPS104" : "CK", "ISO2" : "CC", "ISO3" : "CCK", "ISON" : "166", "Internet" : "CC", "Capital" : "West Island ", "MapReference" : "Southeast Asia ", "NationalitySingular" : "Cocos Islander", "NationalityPlural" : "Cocos Islanders", "Currency" : "Australian Dollar ", "CurrencyCode" : "AUD", "Population" : 633, "Title" : "The Cocos Islands", "Comment" : "" }
{ "_id" : { "$oid" : "50bebfcb14b6500c5cb797cf" }, "CountryId" : 53, "Country" : "Colombia", "FIPS104" : "CO", "ISO2" : "CO", "ISO3" : "COL", "ISON" : "170", "Internet" : "CO", "Capital" : "Bogota ", "MapReference" : "South America, Central America and the Caribbean ", "NationalitySingular" : "Colombian", "NationalityPlural" : "Colombians", "Currency" : "Colombian Peso ", "CurrencyCode" : "COP", "Population" : 40349388, "Title" : "Colombia", "Comment" : "" }
{ "_id" : { "$oid" : "50bebfcb14b6500c5cb797d0" }, "CountryId" : 54, "Country" : "Comoros", "FIPS104" : "CN", "ISO2" : "KM", "ISO3" : "COM", "ISON" : "174", "Internet" : "KM", "Capital" : "Moroni ", "MapReference" : "Africa ", "NationalitySingular" : "Comoran", "NationalityPlural" : "Comorans", "Currency" : "Comoro Franc", "CurrencyCode" : "KMF", "Population" : 596202, "Title" : "Comoros", "Comment" : "" }
{ "_id" : { "$oid" : "50bebfcc14b6500c5cb797d1" }, "CountryId" : 55, "Country" : "Congo, Democratic Republic of the", "FIPS104" : "CG", "ISO2" : "CD", "ISO3" : "COD", "ISON" : "180", "Internet" : "CD", "Capital" : "Kinshasa ", "MapReference" : "Africa ", "NationalitySingular" : "Congolese", "NationalityPlural" : "Congolese", "Currency" : "Franc Congolais", "CurrencyCode" : "CDF", "Population" : 53624718, "Title" : "Democratic Republic of the Congo", "Comment" : "formerly Zaire" }
{ "_id" : { "$oid" : "50bebfcc14b6500c5cb797d2" }, "CountryId" : 56, "Country" : "Congo, Republic of the", "FIPS104" : "CF", "ISO2" : "CG", "ISO3" : "COG", "ISON" : "178", "Internet" : "CG", "Capital" : "Brazzaville ", "MapReference" : "Africa ", "NationalitySingular" : "Congolese", "NationalityPlural" : "Congolese", "Currency" : "CFA Franc BEAC", "CurrencyCode" : "XAF", "Population" : 2894336, "Title" : "Republic of the Congo", "Comment" : "" }
{ "_id" : { "$oid" : "50bebfcd14b6500c5cb797d3" }, "CountryId" : 57, "Country" : "Cook Islands", "FIPS104" : "CW", "ISO2" : "CK", "ISO3" : "COK", "ISON" : "184", "Internet" : "CK", "Capital" : "Avarua ", "MapReference" : "Oceania ", "NationalitySingular" : "Cook Islander", "NationalityPlural" : "Cook Islanders", "Currency" : "New Zealand Dollar ", "CurrencyCode" : "NZD", "Population" : 20611, "Title" : "The Cook Islands", "Comment" : "" }
{ "_id" : { "$oid" : "50bebfcd14b6500c5cb797d4" }, "CountryId" : 58, "Country" : "Coral Sea Islands", "FIPS104" : "CR", "ISO2" : "--", "ISO3" : "-- ", "ISON" : "--", "Internet" : "--", "Capital" : "", "MapReference" : "Oceania ", "NationalitySingular" : "", "NationalityPlural" : "", "Currency" : "", "CurrencyCode" : "", "Population" : 0, "Title" : "The Coral Sea Islands", "Comment" : "ISO includes with Australia" }
{ "_id" : { "$oid" : "50bebfcd14b6500c5cb797d5" }, "CountryId" : 59, "Country" : "Costa Rica", "FIPS104" : "CS", "ISO2" : "CR", "ISO3" : "CRI", "ISON" : "188", "Internet" : "CR", "Capital" : "San Jose ", "MapReference" : "Central America and the Caribbean ", "NationalitySingular" : "Costa Rican", "NationalityPlural" : "Costa Ricans", "Currency" : "Costa Rican Colon", "CurrencyCode" : "CRC", "Population" : 3773057, "Title" : "Costa Rica", "Comment" : "" }
{ "_id" : { "$oid" : "50bebfce14b6500c5cb797d6" }, "CountryId" : 60, "Country" : "Cote d'Ivoire", "FIPS104" : "IV", "ISO2" : "CI", "ISO3" : "CIV", "ISON" : "384", "Internet" : "CI", "Capital" : "Yamoussoukro", "MapReference" : "Africa ", "NationalitySingular" : "Ivorian", "NationalityPlural" : "Ivorians", "Currency" : "CFA Franc BCEAO", "CurrencyCode" : "XOF", "Population" : 16393221, "Title" : "Cote d'Ivoire", "Comment" : "" }
{ "_id" : { "$oid" : "50bebfce14b6500c5cb797d7" }, "CountryId" : 61, "Country" : "Croatia", "FIPS104" : "HR", "ISO2" : "HR", "ISO3" : "HRV", "ISON" : "191", "Internet" : "HR", "Capital" : "Zagreb ", "MapReference" : "Europe ", "NationalitySingular" : "Croatian", "NationalityPlural" : "Croats", "Currency" : "Kuna", "CurrencyCode" : "HRK", "Population" : 4334142, "Title" : "Croatia", "Comment" : "" }
{ "_id" : { "$oid" : "50bebfd014b6500c5cb797d8" }, "CountryId" : 62, "Country" : "Cuba", "FIPS104" : "CU", "ISO2" : "CU", "ISO3" : "CUB", "ISON" : "192", "Internet" : "CU", "Capital" : "Havana ", "MapReference" : "Central America and the Caribbean ", "NationalitySingular" : "Cuban", "NationalityPlural" : "Cubans", "Currency" : "Cuban Peso", "CurrencyCode" : "CUP", "Population" : 11184023, "Title" : "Cuba", "Comment" : "" }
{ "_id" : { "$oid" : "50bebfd014b6500c5cb797d9" }, "CountryId" : 63, "Country" : "Cyprus", "FIPS104" : "CY", "ISO2" : "CY", "ISO3" : "CYP", "ISON" : "196", "Internet" : "CY", "Capital" : "Nicosia ", "MapReference" : "Middle East ", "NationalitySingular" : "Cypriot", "NationalityPlural" : "Cypriots", "Currency" : "Cyprus Pound", "CurrencyCode" : "CYP", "Population" : 762887, "Title" : "Cyprus", "Comment" : "" }
{ "_id" : { "$oid" : "50bebfd114b6500c5cb797da" }, "CountryId" : 64, "Country" : "Czech Republic", "FIPS104" : "EZ", "ISO2" : "CZ", "ISO3" : "CZE", "ISON" : "203", "Internet" : "CZ", "Capital" : "Prague ", "MapReference" : "Europe ", "NationalitySingular" : "Czech", "NationalityPlural" : "Czechs", "Currency" : "Czech Koruna", "CurrencyCode" : "CZK", "Population" : 10264212, "Title" : "The Czech Republic", "Comment" : "" }
{ "_id" : { "$oid" : "50bebfd114b6500c5cb797db" }, "CountryId" : 65, "Country" : "Denmark", "FIPS104" : "DA", "ISO2" : "DK", "ISO3" : "DNK", "ISON" : "208", "Internet" : "DK", "Capital" : "Copenhagen ", "MapReference" : "Europe ", "NationalitySingular" : "Danish", "NationalityPlural" : "Danes", "Currency" : "Danish Krone", "CurrencyCode" : "DKK", "Population" : 5352815, "Title" : "Denmark", "Comment" : "" }
{ "_id" : { "$oid" : "50bebfd214b6500c5cb797dc" }, "CountryId" : 66, "Country" : "Djibouti", "FIPS104" : "DJ", "ISO2" : "DJ", "ISO3" : "DJI", "ISON" : "262", "Internet" : "DJ", "Capital" : "Djibouti ", "MapReference" : "Africa ", "NationalitySingular" : "Djiboutian", "NationalityPlural" : "Djiboutians", "Currency" : "Djibouti Franc", "CurrencyCode" : "DJF", "Population" : 460700, "Title" : "Djibouti", "Comment" : "" }
{ "_id" : { "$oid" : "50bebfd214b6500c5cb797dd" }, "CountryId" : 67, "Country" : "Dominica", "FIPS104" : "DO", "ISO2" : "DM", "ISO3" : "DMA", "ISON" : "212", "Internet" : "DM", "Capital" : "Roseau ", "MapReference" : "Central America and the Caribbean ", "NationalitySingular" : "Dominican", "NationalityPlural" : "Dominicans", "Currency" : "East Caribbean Dollar", "CurrencyCode" : "XCD", "Population" : 70786, "Title" : "Dominica", "Comment" : "" }
{ "_id" : { "$oid" : "50bebfd214b6500c5cb797de" }, "CountryId" : 68, "Country" : "Dominican Republic", "FIPS104" : "DR", "ISO2" : "DO", "ISO3" : "DOM", "ISON" : "214", "Internet" : "DO", "Capital" : "Santo Domingo ", "MapReference" : "Central America and the Caribbean ", "NationalitySingular" : "Dominican", "NationalityPlural" : "Dominicans", "Currency" : "Dominican Peso", "CurrencyCode" : "DOP", "Population" : 8581477, "Title" : "The Dominican Republic", "Comment" : "" }
{ "_id" : { "$oid" : "50bebfd314b6500c5cb797df" }, "CountryId" : 69, "Country" : "East Timor", "FIPS104" : "TT", "ISO2" : "TL", "ISO3" : "TLS", "ISON" : "626", "Internet" : "TP", "Capital" : "", "MapReference" : "", "NationalitySingular" : "", "NationalityPlural" : "", "Currency" : "Timor Escudo", "CurrencyCode" : "TPE", "Population" : 1040880, "Title" : "East Timor", "Comment" : "NULL" }
{ "_id" : { "$oid" : "50bebfd314b6500c5cb797e0" }, "CountryId" : 70, "Country" : "Ecuador", "FIPS104" : "EC", "ISO2" : "EC", "ISO3" : "ECU", "ISON" : "218", "Internet" : "EC", "Capital" : "Quito ", "MapReference" : "South America ", "NationalitySingular" : "Ecuadorian", "NationalityPlural" : "Ecuadorians", "Currency" : "US Dollar", "CurrencyCode" : "USD", "Population" : 13183978, "Title" : "Ecuador", "Comment" : "" }
{ "_id" : { "$oid" : "50bebfd414b6500c5cb797e1" }, "CountryId" : 71, "Country" : "Egypt", "FIPS104" : "EG", "ISO2" : "EG", "ISO3" : "EGY", "ISON" : "818", "Internet" : "EG", "Capital" : "Cairo ", "MapReference" : "Africa ", "NationalitySingular" : "Egyptian", "NationalityPlural" : "Egyptians", "Currency" : "Egyptian Pound ", "CurrencyCode" : "EGP", "Population" : 69536644, "Title" : "Egypt", "Comment" : "" }
{ "_id" : { "$oid" : "50bebfd414b6500c5cb797e2" }, "CountryId" : 72, "Country" : "El Salvador", "FIPS104" : "ES", "ISO2" : "SV", "ISO3" : "SLV", "ISON" : "222", "Internet" : "SV", "Capital" : "San Salvador ", "MapReference" : "Central America and the Caribbean ", "NationalitySingular" : "Salvadoran", "NationalityPlural" : "Salvadorans", "Currency" : "El Salvador Colon", "CurrencyCode" : "SVC", "Population" : 6237662, "Title" : "El Salvador", "Comment" : "" }
{ "_id" : { "$oid" : "50bebfd514b6500c5cb797e3" }, "CountryId" : 73, "Country" : "Equatorial Guinea", "FIPS104" : "EK", "ISO2" : "GQ", "ISO3" : "GNQ", "ISON" : "226", "Internet" : "GQ", "Capital" : "Malabo ", "MapReference" : "Africa ", "NationalitySingular" : "Equatorial Guinean", "NationalityPlural" : "Equatorial Guineans", "Currency" : "CFA Franc BEAC", "CurrencyCode" : "XAF", "Population" : 486060, "Title" : "Equatorial Guinea", "Comment" : "" }
{ "_id" : { "$oid" : "50bebfd514b6500c5cb797e4" }, "CountryId" : 74, "Country" : "Eritrea", "FIPS104" : "ER", "ISO2" : "ER", "ISO3" : "ERI", "ISON" : "232", "Internet" : "ER", "Capital" : "Asmara ", "MapReference" : "Africa ", "NationalitySingular" : "Eritrean", "NationalityPlural" : "Eritreans", "Currency" : "Nakfa", "CurrencyCode" : "ERN", "Population" : 4298269, "Title" : "Eritrea", "Comment" : "" }
{ "_id" : { "$oid" : "50bebfd514b6500c5cb797e5" }, "CountryId" : 75, "Country" : "Estonia", "FIPS104" : "EN", "ISO2" : "EE", "ISO3" : "EST", "ISON" : "233", "Internet" : "EE", "Capital" : "Tallinn ", "MapReference" : "Europe ", "NationalitySingular" : "Estonian", "NationalityPlural" : "Estonians", "Currency" : "Kroon", "CurrencyCode" : "EEK", "Population" : 1423316, "Title" : "Estonia", "Comment" : "" }
{ "_id" : { "$oid" : "50bebfd614b6500c5cb797e6" }, "CountryId" : 76, "Country" : "Ethiopia", "FIPS104" : "ET", "ISO2" : "ET", "ISO3" : "ETH", "ISON" : "231", "Internet" : "ET", "Capital" : "Addis Ababa ", "MapReference" : "Africa ", "NationalitySingular" : "Ethiopian", "NationalityPlural" : "Ethiopians", "Currency" : "Ethiopian Birr", "CurrencyCode" : "ETB", "Population" : 65891874, "Title" : "Ethiopia", "Comment" : "" }
{ "_id" : { "$oid" : "50bebfd614b6500c5cb797e7" }, "CountryId" : 77, "Country" : "Europa Island", "FIPS104" : "EU", "ISO2" : "--", "ISO3" : "-- ", "ISON" : "--", "Internet" : "--", "Capital" : "", "MapReference" : "Africa ", "NationalitySingular" : "", "NationalityPlural" : "", "Currency" : "", "CurrencyCode" : "", "Population" : 0, "Title" : "Europa Island", "Comment" : "ISO includes with the Miscellaneous (French) Indian Ocean Islands" }
{ "_id" : { "$oid" : "50bebfd714b6500c5cb797e8" }, "CountryId" : 78, "Country" : "Falkland Islands (Islas Malvinas)", "FIPS104" : "FK", "ISO2" : "FK", "ISO3" : "FLK", "ISON" : "238", "Internet" : "FK", "Capital" : "Stanley", "MapReference" : "South America", "NationalitySingular" : "Falkland Island", "NationalityPlural" : "Falkland Islanders", "Currency" : "Falkland Islands Pound", "CurrencyCode" : "FKP", "Population" : 2895, "Title" : "The Falkland Islands ", "Comment" : "" }
{ "_id" : { "$oid" : "50bebfd714b6500c5cb797e9" }, "CountryId" : 79, "Country" : "Faroe Islands", "FIPS104" : "FO", "ISO2" : "FO", "ISO3" : "FRO", "ISON" : "234", "Internet" : "FO", "Capital" : "Torshavn ", "MapReference" : "Europe ", "NationalitySingular" : "Faroese", "NationalityPlural" : "Faroese", "Currency" : "Danish Krone ", "CurrencyCode" : "DKK", "Population" : 45661, "Title" : "The Faroe Islands", "Comment" : "" }
{ "_id" : { "$oid" : "50bebfd714b6500c5cb797ea" }, "CountryId" : 80, "Country" : "Fiji", "FIPS104" : "FJ", "ISO2" : "FJ", "ISO3" : "FJI", "ISON" : "242", "Internet" : "FJ", "Capital" : "Suva ", "MapReference" : "Oceania ", "NationalitySingular" : "Fijian", "NationalityPlural" : "Fijians", "Currency" : "Fijian Dollar ", "CurrencyCode" : "FJD", "Population" : 844330, "Title" : "Fiji", "Comment" : "" }
{ "_id" : { "$oid" : "50bebfd814b6500c5cb797eb" }, "CountryId" : 81, "Country" : "Finland", "FIPS104" : "FI", "ISO2" : "FI", "ISO3" : "FIN", "ISON" : "246", "Internet" : "FI", "Capital" : "Helsinki ", "MapReference" : "Europe ", "NationalitySingular" : "Finnish", "NationalityPlural" : "Finns", "Currency" : "Euro", "CurrencyCode" : "EUR", "Population" : 5175783, "Title" : "Finland", "Comment" : "" }
{ "_id" : { "$oid" : "50bebfd814b6500c5cb797ec" }, "CountryId" : 82, "Country" : "France", "FIPS104" : "FR", "ISO2" : "FR", "ISO3" : "FRA", "ISON" : "250", "Internet" : "FR", "Capital" : "Paris ", "MapReference" : "Europe ", "NationalitySingular" : "Frenchman", "NationalityPlural" : "Frenchmen", "Currency" : "Euro", "CurrencyCode" : "EUR", "Population" : 59551227, "Title" : "France", "Comment" : "" }
{ "_id" : { "$oid" : "50bebfd914b6500c5cb797ed" }, "CountryId" : 83, "Country" : "France, Metropolitan", "FIPS104" : "--", "ISO2" : "--", "ISO3" : "-- ", "ISON" : "--", "Internet" : "FX", "Capital" : "", "MapReference" : "", "NationalitySingular" : "", "NationalityPlural" : "", "Currency" : "Euro", "CurrencyCode" : "EUR", "Population" : 0, "Title" : "Metropolitan France", "Comment" : "ISO limits to the European part of France, excluding French Guiana, French Polynesia, French Southern and Antarctic Lands, Guadeloupe, Martinique, Mayotte, New Caledonia, Reunion, Saint Pierre and Miquelon, Wallis and Futuna" }
{ "_id" : { "$oid" : "50bebfda14b6500c5cb797ee" }, "CountryId" : 84, "Country" : "French Guiana", "FIPS104" : "FG", "ISO2" : "GF", "ISO3" : "GUF", "ISON" : "254", "Internet" : "GF", "Capital" : "Cayenne ", "MapReference" : "South America ", "NationalitySingular" : "French Guianese", "NationalityPlural" : "French Guianese", "Currency" : "Euro", "CurrencyCode" : "EUR", "Population" : 177562, "Title" : "French Guiana", "Comment" : "" }
{ "_id" : { "$oid" : "50bebfda14b6500c5cb797ef" }, "CountryId" : 85, "Country" : "French Polynesia", "FIPS104" : "FP", "ISO2" : "PF", "ISO3" : "PYF", "ISON" : "258", "Internet" : "PF", "Capital" : "Papeete ", "MapReference" : "Oceania ", "NationalitySingular" : "French Polynesian", "NationalityPlural" : "French Polynesians", "Currency" : "CFP Franc", "CurrencyCode" : "XPF", "Population" : 253506, "Title" : "French Polynesia", "Comment" : "ISO includes Clipperton Island" }
{ "_id" : { "$oid" : "50bebfdb14b6500c5cb797f0" }, "CountryId" : 86, "Country" : "French Southern and Antarctic Lands", "FIPS104" : "FS", "ISO2" : "TF", "ISO3" : "ATF", "ISON" : "260", "Internet" : "TF", "Capital" : "", "MapReference" : "Antarctic Region ", "NationalitySingular" : "", "NationalityPlural" : "", "Currency" : "Euro", "CurrencyCode" : "EUR", "Population" : 0, "Title" : "The French Southern and Antarctic Lands", "Comment" : "FIPS 10-4 does not include the French-claimed portion of Antarctica (Terre Adelie)" }
{ "_id" : { "$oid" : "50bebfdb14b6500c5cb797f1" }, "CountryId" : 87, "Country" : "Gabon", "FIPS104" : "GB", "ISO2" : "GA", "ISO3" : "GAB", "ISON" : "266", "Internet" : "GA", "Capital" : "Libreville ", "MapReference" : "Africa ", "NationalitySingular" : "Gabonese", "NationalityPlural" : "Gabonese", "Currency" : "CFA Franc BEAC", "CurrencyCode" : "XAF", "Population" : 1221175, "Title" : "Gabon", "Comment" : "" }
{ "_id" : { "$oid" : "50bebfdb14b6500c5cb797f2" }, "CountryId" : 88, "Country" : "The Gambia", "FIPS104" : "GA", "ISO2" : "GM", "ISO3" : "GMB", "ISON" : "270", "Internet" : "GM", "Capital" : "Banjul ", "MapReference" : "Africa ", "NationalitySingular" : "Gambian", "NationalityPlural" : "Gambians", "Currency" : "Dalasi", "CurrencyCode" : "GMD", "Population" : 1411205, "Title" : "The Gambia", "Comment" : "" }
{ "_id" : { "$oid" : "50bebfdc14b6500c5cb797f3" }, "CountryId" : 89, "Country" : "Gaza Strip", "FIPS104" : "GZ", "ISO2" : "--", "ISO3" : "-- ", "ISON" : "--", "Internet" : "--", "Capital" : "", "MapReference" : "Middle East ", "NationalitySingular" : "", "NationalityPlural" : "", "Currency" : "New Israeli Shekel ", "CurrencyCode" : "ILS", "Population" : 1178119, "Title" : "The Gaza Strip", "Comment" : "" }
{ "_id" : { "$oid" : "50bebfdc14b6500c5cb797f4" }, "CountryId" : 90, "Country" : "Georgia", "FIPS104" : "GG", "ISO2" : "GE", "ISO3" : "GEO", "ISON" : "268", "Internet" : "GE", "Capital" : "T'bilisi ", "MapReference" : "Commonwealth of Independent States ", "NationalitySingular" : "Georgian", "NationalityPlural" : "Georgians", "Currency" : "Lari", "CurrencyCode" : "GEL", "Population" : 4989285, "Title" : "Georgia", "Comment" : "" }
{ "_id" : { "$oid" : "50bebfdc14b6500c5cb797f5" }, "CountryId" : 92, "Country" : "Ghana", "FIPS104" : "GH", "ISO2" : "GH", "ISO3" : "GHA", "ISON" : "288", "Internet" : "GH", "Capital" : "Accra ", "MapReference" : "Africa ", "NationalitySingular" : "Ghanaian", "NationalityPlural" : "Ghanaians", "Currency" : "Cedi", "CurrencyCode" : "GHC", "Population" : 19894014, "Title" : "Ghana", "Comment" : "" }
{ "_id" : { "$oid" : "50bebfdd14b6500c5cb797f6" }, "CountryId" : 93, "Country" : "Gibraltar", "FIPS104" : "GI", "ISO2" : "GI", "ISO3" : "GIB", "ISON" : "292", "Internet" : "GI", "Capital" : "Gibraltar ", "MapReference" : "Europe ", "NationalitySingular" : "Gibraltar", "NationalityPlural" : "Gibraltarians", "Currency" : "Gibraltar Pound", "CurrencyCode" : "GIP", "Population" : 27649, "Title" : "Gibraltar", "Comment" : "" }
{ "_id" : { "$oid" : "50bebfdd14b6500c5cb797f7" }, "CountryId" : 94, "Country" : "Glorioso Islands", "FIPS104" : "GO", "ISO2" : "--", "ISO3" : "-- ", "ISON" : "--", "Internet" : "--", "Capital" : "", "MapReference" : "Africa ", "NationalitySingular" : "", "NationalityPlural" : "", "Currency" : "", "CurrencyCode" : "", "Population" : 0, "Title" : "The Glorioso Islands", "Comment" : "ISO includes with the Miscellaneous (French) Indian Ocean Islands" }
{ "_id" : { "$oid" : "50bebfdd14b6500c5cb797f8" }, "CountryId" : 95, "Country" : "Greece", "FIPS104" : "GR", "ISO2" : "GR", "ISO3" : "GRC", "ISON" : "300", "Internet" : "GR", "Capital" : "Athens ", "MapReference" : "Europe ", "NationalitySingular" : "Greek", "NationalityPlural" : "Greeks", "Currency" : "Euro", "CurrencyCode" : "EUR", "Population" : 10623835, "Title" : "Greece", "Comment" : "" }
{ "_id" : { "$oid" : "50bebfde14b6500c5cb797f9" }, "CountryId" : 96, "Country" : "Greenland", "FIPS104" : "GL", "ISO2" : "GL", "ISO3" : "GRL", "ISON" : "304", "Internet" : "GL", "Capital" : "Nuuk ", "MapReference" : "Arctic Region ", "NationalitySingular" : "Greenlandic", "NationalityPlural" : "Greenlanders", "Currency" : "Danish Krone", "CurrencyCode" : "DKK", "Population" : 56352, "Title" : "Greenland", "Comment" : "" }
{ "_id" : { "$oid" : "50bebfde14b6500c5cb797fa" }, "CountryId" : 97, "Country" : "Grenada", "FIPS104" : "GJ", "ISO2" : "GD", "ISO3" : "GRD", "ISON" : "308", "Internet" : "GD", "Capital" : "Saint George's ", "MapReference" : "Central America and the Caribbean ", "NationalitySingular" : "Grenadian", "NationalityPlural" : "Grenadians", "Currency" : "East Caribbean Dollar", "CurrencyCode" : "XCD", "Population" : 89227, "Title" : "Grenada", "Comment" : "" }
{ "_id" : { "$oid" : "50bebfde14b6500c5cb797fb" }, "CountryId" : 98, "Country" : "Guadeloupe", "FIPS104" : "GP", "ISO2" : "GP", "ISO3" : "GLP", "ISON" : "312", "Internet" : "GP", "Capital" : "Basse-Terre ", "MapReference" : "Central America and the Caribbean ", "NationalitySingular" : "Guadeloupe", "NationalityPlural" : "Guadeloupians", "Currency" : "Euro", "CurrencyCode" : "EUR", "Population" : 431170, "Title" : "Guadeloupe", "Comment" : "" }
{ "_id" : { "$oid" : "50bebfdf14b6500c5cb797fc" }, "CountryId" : 99, "Country" : "Guam", "FIPS104" : "GQ", "ISO2" : "GU", "ISO3" : "GUM", "ISON" : "316", "Internet" : "GU", "Capital" : "Hagatna", "MapReference" : "Oceania ", "NationalitySingular" : "Guamanian", "NationalityPlural" : "Guamanians", "Currency" : "US Dollar", "CurrencyCode" : "USD", "Population" : 157557, "Title" : "Guam", "Comment" : "" }
{ "_id" : { "$oid" : "50bebfdf14b6500c5cb797fd" }, "CountryId" : 100, "Country" : "Guatemala", "FIPS104" : "GT", "ISO2" : "GT", "ISO3" : "GTM", "ISON" : "320", "Internet" : "GT", "Capital" : "Guatemala ", "MapReference" : "Central America and the Caribbean ", "NationalitySingular" : "Guatemalan", "NationalityPlural" : "Guatemalans", "Currency" : "Quetzal", "CurrencyCode" : "GTQ", "Population" : 12974361, "Title" : "Guatemala", "Comment" : "" }
{ "_id" : { "$oid" : "50bebfe014b6500c5cb797fe" }, "CountryId" : 101, "Country" : "Guernsey", "FIPS104" : "GK", "ISO2" : "--", "ISO3" : "-- ", "ISON" : "--", "Internet" : "GG", "Capital" : "Saint Peter Port ", "MapReference" : "Europe ", "NationalitySingular" : "Channel Islander", "NationalityPlural" : "Channel Islanders", "Currency" : "Pound Sterling", "CurrencyCode" : "GBP", "Population" : 64342, "Title" : "Guernsey", "Comment" : "ISO includes with the United Kingdom" }
{ "_id" : { "$oid" : "50bebfe014b6500c5cb797ff" }, "CountryId" : 102, "Country" : "Guinea", "FIPS104" : "GV", "ISO2" : "GN", "ISO3" : "GIN", "ISON" : "324", "Internet" : "GN", "Capital" : "Conakry ", "MapReference" : "Africa ", "NationalitySingular" : "Guinean", "NationalityPlural" : "Guineans", "Currency" : "Guinean Franc ", "CurrencyCode" : "GNF", "Population" : 7613870, "Title" : "Guinea", "Comment" : "" }
{ "_id" : { "$oid" : "50bebfe014b6500c5cb79800" }, "CountryId" : 103, "Country" : "Guinea-Bissau", "FIPS104" : "PU", "ISO2" : "GW", "ISO3" : "GNB", "ISON" : "624", "Internet" : "GW", "Capital" : "Bissau ", "MapReference" : "Africa ", "NationalitySingular" : "Guinean", "NationalityPlural" : "Guineans", "Currency" : "CFA Franc BCEAO", "CurrencyCode" : "XOF", "Population" : 1315822, "Title" : "Guinea-Bissau", "Comment" : "" }
{ "_id" : { "$oid" : "50bebfe114b6500c5cb79801" }, "CountryId" : 104, "Country" : "Guyana", "FIPS104" : "GY", "ISO2" : "GY", "ISO3" : "GUY", "ISON" : "328", "Internet" : "GY", "Capital" : "Georgetown ", "MapReference" : "South America ", "NationalitySingular" : "Guyanese", "NationalityPlural" : "Guyanese", "Currency" : "Guyana Dollar", "CurrencyCode" : "GYD", "Population" : 697181, "Title" : "Guyana", "Comment" : "" }
{ "_id" : { "$oid" : "50bebfe114b6500c5cb79802" }, "CountryId" : 105, "Country" : "Haiti", "FIPS104" : "HA", "ISO2" : "HT", "ISO3" : "HTI", "ISON" : "332", "Internet" : "HT", "Capital" : "Port-au-Prince ", "MapReference" : "Central America and the Caribbean ", "NationalitySingular" : "Haitian", "NationalityPlural" : "Haitians", "Currency" : "Gourde", "CurrencyCode" : "HTG", "Population" : 6964549, "Title" : "Haiti", "Comment" : "" }
{ "_id" : { "$oid" : "50bebfe114b6500c5cb79803" }, "CountryId" : 106, "Country" : "Heard Island and McDonald Islands", "FIPS104" : "HM", "ISO2" : "HM", "ISO3" : "HMD", "ISON" : "334", "Internet" : "HM", "Capital" : "", "MapReference" : "Antarctic Region ", "NationalitySingular" : "", "NationalityPlural" : "", "Currency" : "Australian Dollar", "CurrencyCode" : "AUD", "Population" : 0, "Title" : "The Heard Island and McDonald Islands", "Comment" : "" }
{ "_id" : { "$oid" : "50bebfe214b6500c5cb79804" }, "CountryId" : 107, "Country" : "Holy See (Vatican City)", "FIPS104" : "VT", "ISO2" : "VA", "ISO3" : "VAT", "ISON" : "336", "Internet" : "VA", "Capital" : "Vatican City ", "MapReference" : "Europe ", "NationalitySingular" : "", "NationalityPlural" : "", "Currency" : "Euro", "CurrencyCode" : "EUR", "Population" : 890, "Title" : "The Vatican City", "Comment" : "" }
{ "_id" : { "$oid" : "50bebfe214b6500c5cb79805" }, "CountryId" : 108, "Country" : "Honduras", "FIPS104" : "HO", "ISO2" : "HN", "ISO3" : "HND", "ISON" : "340", "Internet" : "HN", "Capital" : "Tegucigalpa ", "MapReference" : "Central America and the Caribbean ", "NationalitySingular" : "Honduran", "NationalityPlural" : "Hondurans", "Currency" : "Lempira", "CurrencyCode" : "HNL", "Population" : 6406052, "Title" : "Honduras", "Comment" : "" }
{ "_id" : { "$oid" : "50bebfe214b6500c5cb79806" }, "CountryId" : 109, "Country" : "Hong Kong (SAR)", "FIPS104" : "HK", "ISO2" : "HK", "ISO3" : "HKG", "ISON" : "344", "Internet" : "HK", "Capital" : "", "MapReference" : "Southeast Asia ", "NationalitySingular" : "", "NationalityPlural" : "", "Currency" : "Hong Kong Dollar ", "CurrencyCode" : "HKD", "Population" : 0, "Title" : "Xianggang ", "Comment" : "" }
{ "_id" : { "$oid" : "50bebfe314b6500c5cb79807" }, "CountryId" : 110, "Country" : "Howland Island", "FIPS104" : "HQ", "ISO2" : "--", "ISO3" : "-- ", "ISON" : "--", "Internet" : "--", "Capital" : "", "MapReference" : "Oceania ", "NationalitySingular" : "", "NationalityPlural" : "", "Currency" : "", "CurrencyCode" : "", "Population" : 7210505, "Title" : "Howland Island", "Comment" : "ISO includes with the US Minor Outlying Islands" }
{ "_id" : { "$oid" : "50bebfe414b6500c5cb79808" }, "CountryId" : 111, "Country" : "Hungary", "FIPS104" : "HU", "ISO2" : "HU", "ISO3" : "HUN", "ISON" : "348", "Internet" : "HU", "Capital" : "Budapest ", "MapReference" : "Europe ", "NationalitySingular" : "Hungarian", "NationalityPlural" : "Hungarians", "Currency" : "Forint", "CurrencyCode" : "HUF", "Population" : 10106017, "Title" : "Hungary", "Comment" : "" }
{ "_id" : { "$oid" : "50bebfe414b6500c5cb79809" }, "CountryId" : 112, "Country" : "Iceland", "FIPS104" : "IC", "ISO2" : "IS", "ISO3" : "ISL", "ISON" : "352", "Internet" : "IS", "Capital" : "Reykjavik ", "MapReference" : "Arctic Region ", "NationalitySingular" : "Icelandic", "NationalityPlural" : "Icelanders", "Currency" : "Iceland Krona", "CurrencyCode" : "ISK", "Population" : 277906, "Title" : "Iceland", "Comment" : "" }
{ "_id" : { "$oid" : "50bebfe414b6500c5cb7980a" }, "CountryId" : 114, "Country" : "Indonesia", "FIPS104" : "ID", "ISO2" : "ID", "ISO3" : "IDN", "ISON" : "360", "Internet" : "ID", "Capital" : "Jakarta ", "MapReference" : "Southeast Asia ", "NationalitySingular" : "Indonesian", "NationalityPlural" : "Indonesians", "Currency" : "Rupiah", "CurrencyCode" : "IDR", "Population" : 228437870, "Title" : "Indonesia", "Comment" : "" }
{ "_id" : { "$oid" : "50bebfe514b6500c5cb7980b" }, "CountryId" : 115, "Country" : "Iran", "FIPS104" : "IR", "ISO2" : "IR", "ISO3" : "IRN", "ISON" : "364", "Internet" : "IR", "Capital" : "Tehran ", "MapReference" : "Middle East ", "NationalitySingular" : "Iranian", "NationalityPlural" : "Iranians", "Currency" : "Iranian Rial", "CurrencyCode" : "IRR", "Population" : 66128965, "Title" : "Iran", "Comment" : "" }
{ "_id" : { "$oid" : "50bebfe514b6500c5cb7980c" }, "CountryId" : 116, "Country" : "Iraq", "FIPS104" : "IZ", "ISO2" : "IQ", "ISO3" : "IRQ", "ISON" : "368", "Internet" : "IQ", "Capital" : "Baghdad ", "MapReference" : "Middle East ", "NationalitySingular" : "Iraqi", "NationalityPlural" : "Iraqis", "Currency" : "Iraqi Dinar", "CurrencyCode" : "IQD", "Population" : 23331985, "Title" : "Iraq", "Comment" : "" }
{ "_id" : { "$oid" : "50bebfe514b6500c5cb7980d" }, "CountryId" : 117, "Country" : "Ireland", "FIPS104" : "EI", "ISO2" : "IE", "ISO3" : "IRL", "ISON" : "372", "Internet" : "IE", "Capital" : "Dublin ", "MapReference" : "Europe ", "NationalitySingular" : "Irish", "NationalityPlural" : "Irishmen", "Currency" : "Euro", "CurrencyCode" : "EUR", "Population" : 3840838, "Title" : "Ireland", "Comment" : "" }
{ "_id" : { "$oid" : "50bebfe614b6500c5cb7980e" }, "CountryId" : 118, "Country" : "Israel", "FIPS104" : "IS", "ISO2" : "IL", "ISO3" : "ISR", "ISON" : "376", "Internet" : "IL", "Capital" : "Jerusalem", "MapReference" : "Middle East ", "NationalitySingular" : "Israeli", "NationalityPlural" : "Israelis", "Currency" : "New Israeli Sheqel", "CurrencyCode" : "ILS", "Population" : 5938093, "Title" : "Israel", "Comment" : "" }
{ "_id" : { "$oid" : "50bebfe614b6500c5cb7980f" }, "CountryId" : 119, "Country" : "Italy", "FIPS104" : "IT", "ISO2" : "IT", "ISO3" : "ITA", "ISON" : "380", "Internet" : "IT", "Capital" : "Rome ", "MapReference" : "Europe ", "NationalitySingular" : "Italian", "NationalityPlural" : "Italians", "Currency" : "Euro", "CurrencyCode" : "EUR", "Population" : 57679825, "Title" : "Italia ", "Comment" : "" }
{ "_id" : { "$oid" : "50bebfe614b6500c5cb79810" }, "CountryId" : 120, "Country" : "Jamaica", "FIPS104" : "JM", "ISO2" : "JM", "ISO3" : "JAM", "ISON" : "388", "Internet" : "JM", "Capital" : "Kingston ", "MapReference" : "Central America and the Caribbean ", "NationalitySingular" : "Jamaican", "NationalityPlural" : "Jamaicans", "Currency" : "Jamaican dollar ", "CurrencyCode" : "JMD", "Population" : 2665636, "Title" : "Jamaica", "Comment" : "" }
